gemerald/__init__.py
gemerald/__main__.py
gemerald/_test___main__.py
gemerald/_test_formatter.py
gemerald/_test_line_elements.py
gemerald/_test_markdown_file.py
gemerald/_test_navigator.py
gemerald/_test_parsing.py
gemerald/elements.py
gemerald/format_config.py
gemerald/formatter.py
gemerald/inline_elements.py
gemerald/line_elements.py
gemerald/markdown_file.py
gemerald/navigator.py
gemerald/strategies/__init__.py
gemerald/strategies/_test___init__.py
gemerald/strategies/_test_plaintext.py
gemerald/strategies/debug.py
gemerald/strategies/gemini.py
gemerald/strategies/html.py
gemerald/strategies/plaintext.py
gemerald/test_dirs/content/.gitkeep
gemerald/test_dirs/static/.gitkeep
gemerald/test_dirs/templates/.gitkeep
gemerald/test_navigator/debug/Comment.txt
gemerald/test_navigator/debug/config.yaml
gemerald/test_navigator/debug/test_file_a.debug
gemerald/test_navigator/debug/test_file_b.debug
gemerald/test_navigator/debug/test_folder/_entries_.debug
gemerald/test_navigator/test_2_folders/folder_a/test_file1
gemerald/test_navigator/test_2_folders/folder_a/subfolder/test_file2
gemerald/test_navigator/test_2_folders/folder_b/test_file1
gemerald/test_navigator/test_2_folders/folder_b/subfolder/test_file2
gemerald/test_navigator/test_content/should_not_be_visible.txt
gemerald/test_navigator/test_content/test_file_a.md
gemerald/test_navigator/test_content/test_file_b.md
gemerald/test_navigator/test_content/test_folder/test_file_c.md
gemerald/test_navigator/test_files/test_file_a.txt
gemerald/test_navigator/test_files/test_file_b.txt
gemerald/test_navigator/test_files/test_folder/test_file_c.txt
gemerald-0.2.dist-info/licenses/LICENSE
gemerald-0.2.dist-info/WHEEL
gemerald-0.2.dist-info/METADATA
gemerald-0.2.dist-info/RECORD
