Metadata-Version: 2.4
Name: gemerald
Version: 0.2
Summary: Markdown-based static site generator
Author-email: Wilmhit <wilmhit@disroot.org>
License-File: LICENSE
Requires-Dist: Jinja2
Requires-Dist: pyYAML
Requires-Dist: pdoc ; extra == "dev"
Requires-Dist: pylint ; extra == "dev"
Requires-Dist: black ; extra == "dev"
Requires-Dist: pytest ; extra == "dev"
Requires-Dist: coverage ; extra == "dev"
Provides-Extra: dev
